pytest_aws_config.py
pytest_aws_config-0.1.0.dist-info/LICENSE
pytest_aws_config-0.1.0.dist-info/METADATA
pytest_aws_config-0.1.0.dist-info/WHEEL
pytest_aws_config-0.1.0.dist-info/entry_points.txt
pytest_aws_config-0.1.0.dist-info/top_level.txt
pytest_aws_config-0.1.0.dist-info/RECORD
