Metadata-Version: 2.1
Name: pytest-aws-config
Version: 0.1.0
Summary: Protect your AWS credentials in unit tests
Home-page: https://github.com/MartinAltmayer/pytest_aws_config
Author: Martin Altmayer
Author-email: martin.altmayer@web.de
License: UNKNOWN
Platform: UNKNOWN
Classifier: Programming Language :: Python :: 3
Classifier: License :: OSI Approved :: MIT License
Classifier: Operating System :: OS Independent
Classifier: Framework :: Pytest
Classifier: Intended Audience :: Developers
Classifier: Topic :: Software Development :: Testing
Requires-Python: >=3.6
License-File: LICENSE
